Metadata-Version: 2.1
Name: swversion
Version: 0.0.1
Summary: Compare software version for network devices: Cisco, HP, etc.
Author-email: Vladimir Prusakov <vladimir.prusakovs@gmail.com>
License: MIT
Project-URL: Homepage, https://github.com/vladimirs-git/swversion
Project-URL: Repository, https://github.com/vladimirs-git/swversion
Project-URL: Bug Tracker, https://github.com/vladimirs-git/swversion/issues
Project-URL: Download URL, https://github.com/vladimirs-git/swversion/archive/refs/tags/0.0.1.tar.gz
Keywords: cisco,ios,networking,telecommunication
Classifier: Development Status :: 5 - Production/Stable
Classifier: Intended Audience :: Developers
Classifier: Intended Audience :: System Administrators
Classifier: Intended Audience :: Telecommunications Industry
Classifier: Topic :: System :: Networking
Classifier: License :: OSI Approved :: MIT License
Classifier: Programming Language :: Python :: 3.8
Classifier: Programming Language :: Python :: 3.9
Classifier: Programming Language :: Python :: 3.10
Classifier: Natural Language :: English
Requires-Python: >=3.8
Provides-Extra: dev
License-File: LICENSE.txt
